setup.py
knight_bus/Receiver.py
knight_bus/Sender.py
knight_bus/__init__.py
knight_bus/base.py
knight_bus.egg-info/PKG-INFO
knight_bus.egg-info/SOURCES.txt
knight_bus.egg-info/dependency_links.txt
knight_bus.egg-info/requires.txt
knight_bus.egg-info/top_level.txt